md_replace.py
md_replace-1.0.1.dist-info/METADATA
md_replace-1.0.1.dist-info/WHEEL
md_replace-1.0.1.dist-info/entry_points.txt
md_replace-1.0.1.dist-info/top_level.txt
md_replace-1.0.1.dist-info/RECORD
