Metadata-Version: 2.1
Name: md-replace
Version: 1.0.1
Summary: Replace file paths in markdown files with the contents of the files.
Home-page: https://your.repository.url
Author: Your Name
Author-email: your.email@example.com
License: UNKNOWN
Platform: UNKNOWN
Classifier: Programming Language :: Python :: 3
Classifier: Operating System :: OS Independent
